.gitignore
MANIFEST.in
README.rst
setup.cfg
setup.py
docs/HISTORY.rst
docs/INSTALL.txt
docs/LICENSE.GPL
docs/LICENSE.txt
pas/__init__.py
pas.plugins.osiris.egg-info/PKG-INFO
pas.plugins.osiris.egg-info/SOURCES.txt
pas.plugins.osiris.egg-info/dependency_links.txt
pas.plugins.osiris.egg-info/entry_points.txt
pas.plugins.osiris.egg-info/namespace_packages.txt
pas.plugins.osiris.egg-info/not-zip-safe
pas.plugins.osiris.egg-info/requires.txt
pas.plugins.osiris.egg-info/top_level.txt
pas/plugins/__init__.py
pas/plugins/osiris/README.txt
pas/plugins/osiris/__init__.py
pas/plugins/osiris/configure.zcml
pas/plugins/osiris/install.py
pas/plugins/osiris/interface.py
pas/plugins/osiris/plugin.py
pas/plugins/osiris/setuphandlers.py
pas/plugins/osiris/tests.py
pas/plugins/osiris/browser/__init__.py
pas/plugins/osiris/browser/add_plugin.zpt
pas/plugins/osiris/browser/configure.zcml
pas/plugins/osiris/browser/icon.gif
pas/plugins/osiris/plugins/__init__.py
pas/plugins/osiris/profiles/default/import_steps.xml
pas/plugins/osiris/profiles/default/metadata.xml
pas/plugins/osiris/profiles/default/osiris_marker.txt