Metadata-Version: 1.1
Name: pas.plugins.osiris
Version: 1.0
Summary: Osiris oauth server PAS plugin.
Home-page: https://github.com/UPCnet/pas.plugins.osiris
Author: UPCnet Plone Team
Author-email: plone.team@upcnet.es
License: gpl
Keywords: plone oauth osiris pas plugin
Platform: UNKNOWN
Classifier: Environment :: Web Environment
Classifier: Framework :: Plone
Classifier: Operating System :: OS Independent
Classifier: Programming Language :: Python
Classifier: Programming Language :: Python :: 2.7
Classifier: Topic :: Software Development :: Libraries :: Python Modules
